odoo/addons/fieldservice_equipment_agreement/README.rst
odoo/addons/fieldservice_equipment_agreement/__init__.py
odoo/addons/fieldservice_equipment_agreement/__manifest__.py
odoo/addons/fieldservice_equipment_agreement/models/__init__.py
odoo/addons/fieldservice_equipment_agreement/models/agreement.py
odoo/addons/fieldservice_equipment_agreement/models/fsm_equipment.py
odoo/addons/fieldservice_equipment_agreement/readme/CONFIGURE.rst
odoo/addons/fieldservice_equipment_agreement/readme/CONTRIBUTORS.rst
odoo/addons/fieldservice_equipment_agreement/readme/CREDITS.rst
odoo/addons/fieldservice_equipment_agreement/readme/DESCRIPTION.rst
odoo/addons/fieldservice_equipment_agreement/readme/ROADMAP.rst
odoo/addons/fieldservice_equipment_agreement/readme/USAGE.rst
odoo/addons/fieldservice_equipment_agreement/static/description/icon.png
odoo/addons/fieldservice_equipment_agreement/static/description/index.html
odoo/addons/fieldservice_equipment_agreement/views/agreement_view.xml
odoo/addons/fieldservice_equipment_agreement/views/fsm_equipment_view.xml
odoo11_addon_fieldservice_equipment_agreement-11.0.1.0.0.99.dev3.dist-info/METADATA
odoo11_addon_fieldservice_equipment_agreement-11.0.1.0.0.99.dev3.dist-info/RECORD
odoo11_addon_fieldservice_equipment_agreement-11.0.1.0.0.99.dev3.dist-info/WHEEL
odoo11_addon_fieldservice_equipment_agreement-11.0.1.0.0.99.dev3.dist-info/top_level.txt
